bidsphysio.edf2bids-21.5.28-py3.8-nspkg.pth
bidsphysio/edf2bids/__init__.py
bidsphysio/edf2bids/edf2bidsphysio.py
bidsphysio/edf2bids/edfsession2bids.py
bidsphysio/edf2bids/info.py
tests/__init__.py
tests/test_edf2bidsphysio.py
tests/test_edfsession2bids.py
tests/utils.py
bidsphysio.edf2bids-21.5.28.dist-info/METADATA
bidsphysio.edf2bids-21.5.28.dist-info/WHEEL
bidsphysio.edf2bids-21.5.28.dist-info/entry_points.txt
bidsphysio.edf2bids-21.5.28.dist-info/namespace_packages.txt
bidsphysio.edf2bids-21.5.28.dist-info/top_level.txt
bidsphysio.edf2bids-21.5.28.dist-info/RECORD
