Metadata-Version: 2.1
Name: bidsphysio.edf2bids
Version: 21.5.28
Summary: EDF-to-BIDS Converter
Home-page: UNKNOWN
Author: Chrysa Papadaniil
Author-email: chrysa@nyu.edu
License: MIT
Platform: UNKNOWN
Classifier: Environment :: Console
Classifier: Intended Audience :: Science/Research
Classifier: License :: OSI Approved :: MIT License
Classifier: Programming Language :: Python :: 3.6
Classifier: Programming Language :: Python :: 3.7
Classifier: Programming Language :: Python :: 3.8
Classifier: Topic :: Scientific/Engineering
Requires-Python: >=3.6
Requires-Dist: bidsphysio.base (>=21.5.18)
Requires-Dist: bidsphysio.session (>=21.5.18)
Requires-Dist: bidsphysio.events (>=21.5.27)
Requires-Dist: h5py (>=2.9.0)
Requires-Dist: Cython (>=0.29.13)
Requires-Dist: pandas (>=1.1.0)
Requires-Dist: numpy (>=1.20.1)
Requires-Dist: pyedfread
Provides-Extra: all
Requires-Dist: pytest ; extra == 'all'
Provides-Extra: tests
Requires-Dist: pytest ; extra == 'tests'
